dataclasses_dict/__init__.py
dataclasses_dict/dataclasses_dict.py
dataclasses_dict-0.0.1.dist-info/METADATA
dataclasses_dict-0.0.1.dist-info/RECORD
dataclasses_dict-0.0.1.dist-info/WHEEL
dataclasses_dict-0.0.1.dist-info/top_level.txt
